LICENSE
MANIFEST.in
README.rst
pyproject.toml
setup.cfg
setup.py
django_societies.egg-info/PKG-INFO
django_societies.egg-info/SOURCES.txt
django_societies.egg-info/dependency_links.txt
django_societies.egg-info/requires.txt
django_societies.egg-info/top_level.txt
societies/__init__.py
societies/admin.py
societies/apps.py
societies/choices.py
societies/models.py
societies/tests.py
societies/views.py
societies/migrations/__init__.py