Metadata-Version: 2.1
Name: django-societies
Version: 0.1.2
Summary: A Django module that provides a collection of abstract models for handling data associated with people, groups, organizations, places, events and means of communication.
Home-page: https://www.schemefusion.com/
Author: Onyeibo Oku
Author-email: onyeibo@schemefusion.com
License: GPLv3
Classifier: Environment :: Web Environment
Classifier: Framework :: Django
Classifier: Framework :: Django :: 4.2
Classifier: Intended Audience :: Developers
Classifier: License :: OSI Approved :: BSD License
Classifier: Operating System :: OS Independent
Classifier: Programming Language :: Python
Classifier: Programming Language :: Python :: 3
Classifier: Programming Language :: Python :: 3 :: Only
Classifier: Programming Language :: Python :: 3.10
Classifier: Programming Language :: Python :: 3.11
Classifier: Programming Language :: Python :: 3.12
Classifier: Topic :: Internet :: WWW/HTTP
Classifier: Topic :: Internet :: WWW/HTTP :: Dynamic Content
Requires-Python: >=3.10
License-File: LICENSE
Requires-Dist: Django>=4.2
